{
    "name": "Jack Y. Araz",
    "job": "Research Scientist",
    "email": "jackaraz@jlab.org",
    "links": [
	{
	    "affiliation": "GitHub",
	    "name": "",
	    "icon": "images/github.svg",
	    "link": "https://github.com/jackaraz"
	},
	{
	    "affiliation": "GitLab",
	    "name": "",
	    "icon": "images/gitlab.svg",
	    "link": "https://gitlab.com/jackaraz"
	},
	{
	    "affiliation": "LinkedIn",
	    "name": "",
	    "icon": "images/linkedin.svg",
	    "link": "https://uk.linkedin.com/in/jackaraz"
	},
	{
	    "affiliation": "INSPIRE-HEP",
	    "name": "",
	    "link": "https://inspirehep.net/authors/1599325"
	},
	{
	    "affiliation": "arXiv",
	    "name": "",
	    "link": "https://arxiv.org/search/hep-ph?searchtype=author&query=Araz%2C+J+Y"
	},
	{
	    "affiliation": "ORCID",
	    "name": "",
	    "link": "https://orcid.org/0000-0001-8721-8042"
	}      
    ],
    "languages": [
	{
	    "name": "Turkish",
	    "level": "Mother Tongue"
	},
	{
	    "name": "English",
	    "level": "Professional Proficiency"
	}
    ],
    "programming": [
	{
	    "name": "Python"
	},
	{
	    "name": "$$ \\texttt{C++} $$"
	},
	{
	    "name": "$$ \\LaTeX $$"
	},
	{
	    "name": "$$ \\texttt{bash script} $$"
	}
    ],
    "image": "images/jack_profile.jpg"
}
